ozekilibsrest/__init__.py
ozekilibsrest-1.8.0.dist-info/LICENSE
ozekilibsrest-1.8.0.dist-info/METADATA
ozekilibsrest-1.8.0.dist-info/WHEEL
ozekilibsrest-1.8.0.dist-info/top_level.txt
ozekilibsrest-1.8.0.dist-info/RECORD
