Metadata-Version: 2.1
Name: ozekilibsrest
Version: 1.8.0
Summary: It is a library, that makes it easier for you to comunicate with the Ozeki SMS Gateway.
Home-page: http://in.ozeki.hu/p_861-python-send-sms-with-the-http-rest-api-code-sample.html
Author: Zsolt Ardai
Author-email: info@ozeki.hu
License: UNKNOWN
Platform: UNKNOWN
Classifier: Programming Language :: Python :: 3
Classifier: License :: OSI Approved :: MIT License
Classifier: Operating System :: OS Independent
Requires-Python: >=3.6
License-File: LICENSE
Requires-Dist: requests
